jessiql/__init__.py
jessiql/engine/__init__.py
jessiql/engine/jselectinloader.py
jessiql/engine/loader.py
jessiql/engine/query.py
jessiql/engine/query_executor.py
jessiql/exc.py
jessiql/features/__init__.py
jessiql/features/cursor/__init__.py
jessiql/features/cursor/cursors/__init__.py
jessiql/features/cursor/cursors/base.py
jessiql/features/cursor/cursors/encode.py
jessiql/features/cursor/cursors/keyset.py
jessiql/features/cursor/cursors/skip.py
jessiql/features/cursor/query.py
jessiql/features/cursor/skiplimit.py
jessiql/integration/__init__.py
jessiql/integration/fastapi/__init__.py
jessiql/integration/fastapi/query_object.py
jessiql/integration/graphql/__init__.py
jessiql/integration/graphql/query_field/__init__.py
jessiql/integration/graphql/query_field/defs.py
jessiql/integration/graphql/query_field/every.py
jessiql/integration/graphql/query_field/sa_model.py
jessiql/integration/graphql/query_object.py
jessiql/integration/graphql/query_object_argument.py
jessiql/integration/graphql/schema.graphql
jessiql/integration/graphql/schema.py
jessiql/integration/graphql/selection.py
jessiql/operations/__init__.py
jessiql/operations/base.py
jessiql/operations/filter.py
jessiql/operations/select.py
jessiql/operations/skiplimit.py
jessiql/operations/sort.py
jessiql/py.typed
jessiql/query_object/__init__.py
jessiql/query_object/base.py
jessiql/query_object/filter.py
jessiql/query_object/limit.py
jessiql/query_object/query_object.py
jessiql/query_object/resolve.py
jessiql/query_object/select.py
jessiql/query_object/skip.py
jessiql/query_object/sort.py
jessiql/sainfo/__init__.py
jessiql/sainfo/columns.py
jessiql/sainfo/models.py
jessiql/sainfo/names.py
jessiql/sainfo/properties.py
jessiql/sainfo/relations.py
jessiql/sainfo/version.py
jessiql/sautil/__init__.py
jessiql/sautil/adapt.py
jessiql/sautil/properties.py
jessiql/testing/__init__.py
jessiql/testing/insert.py
jessiql/testing/profile.py
jessiql/testing/recreate_tables.py
jessiql/testing/stmt_text.py
jessiql/typing.py
jessiql-0.0.1.dist-info/LICENSE
jessiql-0.0.1.dist-info/WHEEL
jessiql-0.0.1.dist-info/METADATA
jessiql-0.0.1.dist-info/RECORD
