Metadata-Version: 2.1
Name: jessiql
Version: 0.0.1
Summary: 
Home-page: https://github.com/kolypto/py-jessiql
Author: Mark Vartanyan
Author-email: kolypto@gmail.com
Requires-Python: >=3.9,<4.0
Classifier: Programming Language :: Python :: 3
Classifier: Programming Language :: Python :: 3.9
Requires-Dist: SQLAlchemy[mypy]
Requires-Dist: fastapi (>=0.51)
Requires-Dist: graphql-core (>=3.0.0)
Project-URL: Repository, https://github.com/kolypto/py-jessiql
